{
  "articles": [],
  "definitif": false,
  "depot": false,
  "expose": "Réunie le mardi 1er août 2017, la commission mixte paritaire a constaté ne pouvoir parvenir à élaborer un texte commun sur les dispositions restant en discussion du projet de loi organique pour la confiance dans la vie politique.",
  "id": "S16-l702",
  "nossenateurs_id": "20162017-702",
  "sections": [],
  "source": "https://www.senat.fr/leg/pjl16-702.html",
  "titre": "projet de loi organique rétablissant la confiance dans l'action publique",
  "type": "texte"
}