{
  "assemblee_id": "15-retablissement_confiance_action_publique",
  "assemblee_legislature": 15,
  "assemblee_slug": "retablissement_confiance_action_publique",
  "beginning": "2017-06-14",
  "end": "2017-09-16",
  "id": "pjl16-580",
  "law_name": "Loi n° 2017-1338 du 15 septembre 2017",
  "legifrance_cidTexte": "JORFTEXT000035567936",
  "long_title": "projet de loi organique pour la confiance dans la vie politique",
  "long_title_descr": "Loi organique pour la confiance dans la vie politique",
  "objet_du_texte": "Pendant la campagne présidentielle, Emmanuel MACRON s'était engagé à présenter plusieurs textes visant à  \"moraliser la vie publique\" afin de \"renforcer le lien qui existe entre les citoyens et leurs représentants\".Présentée le 14 juin en Conseil des ministres et déposée le même jour devant le Sénat, la réforme se décline en deux volets : un projet loi organique et un projet de loi ordinaire.Elle comporte notamment des dispositions relatives :- au financement de la vie politique, avec un renforcement du contrôle des comptes des partis politiques et un encadrement de leur financement et de celui des campagnes électorales ;- à l'exercice du mandat parlementaire, en matière de prévention et de cessation des conflits d'intérêts et de cumul de fonctions, notamment s'agissant de l'activité de conseil ;- aux conditions d'embauche et de nomination des collaborateurs des membres du Gouvernement, des parlementaires et des titulaires de fonctions exécutives locales ;- à l'inéligibilité en cas de crimes ou d'infractions traduisant des manquements à la probité pour les candidats aux élections législatives et sénatoriales.",
  "proposal_type": "PJL",
  "senat_id": "pjl16-580",
  "short_title": "Confiance dans la vie politique (texte organique)",
  "stats": {
    "echecs_procedure": 1,
    "input_text_length": 20181,
    "last_stage": "l. définitive",
    "output_text_length": 75985,
    "ratio_articles_growth": 1.9285714285714286,
    "ratio_texte_modif": 0.7778258554120623,
    "total_amendements": 842,
    "total_amendements_adoptes": 191,
    "total_amendements_gouvernement": 31,
    "total_amendements_gouvernement_adoptes": 18,
    "total_amendements_parlementaire": 811,
    "total_amendements_parlementaire_adoptes": 173,
    "total_days": 95,
    "total_input_articles": 14,
    "total_intervenants": 344,
    "total_interventions": 11719,
    "total_mots": 1142651,
    "total_output_articles": 27
  },
  "steps": [
    {
      "auteur_depot": "Gouvernement",
      "date": "2017-06-14",
      "debats_order": 0,
      "directory": "00_1erelecture_senat_depot",
      "echec": null,
      "enddate": "2017-06-14",
      "institution": "senat",
      "source_url": "https://www.senat.fr/leg/pjl16-580.html",
      "stage": "1ère lecture",
      "step": "depot"
    },
    {
      "date": "2017-07-04",
      "debats_order": 1,
      "directory": "01_1erelecture_senat_commission",
      "echec": null,
      "enddate": "2017-07-04",
      "institution": "senat",
      "nb_amendements": 90,
      "source_url": "https://www.senat.fr/leg/pjl16-608.html",
      "stage": "1ère lecture",
      "step": "commission"
    },
    {
      "date": "2017-07-10",
      "debats_order": 2,
      "directory": "02_1erelecture_senat_hemicycle",
      "echec": null,
      "enddate": "2017-07-13",
      "has_interventions": true,
      "institution": "senat",
      "intervention_files": [
        "2017-07-10T16:00_16415",
        "2017-07-11T14:15_16431",
        "2017-07-12T14:30_16433",
        "2017-07-13T09:30_16435"
      ],
      "nb_amendements": 82,
      "source_url": "https://www.senat.fr/leg/tas16-114.html",
      "stage": "1ère lecture",
      "step": "hemicycle"
    },
    {
      "date": "2017-07-13",
      "debats_order": null,
      "directory": "03_1erelecture_assemblee_depot",
      "enddate": "2017-07-13",
      "institution": "assemblee",
      "source_url": "http://www.assemblee-nationale.fr/15/projets/pl0099.asp",
      "stage": "1ère lecture",
      "step": "depot"
    },
    {
      "date": "2017-07-20",
      "debats_order": 4,
      "directory": "04_1erelecture_assemblee_commission",
      "echec": null,
      "enddate": "2017-07-20",
      "institution": "assemblee",
      "nb_amendements": 144,
      "source_url": "http://www.assemblee-nationale.fr/15/ta-commission/r0105-a0.asp",
      "stage": "1ère lecture",
      "step": "commission"
    },
    {
      "date": "2017-07-24",
      "debats_order": 5,
      "directory": "05_1erelecture_assemblee_hemicycle",
      "echec": null,
      "enddate": "2017-07-28",
      "has_interventions": true,
      "institution": "assemblee",
      "intervention_files": [
        "2017-07-24T16:00_84",
        "2017-07-24T21:30_85",
        "2017-07-25T15:00_101",
        "2017-07-25T21:30_102",
        "2017-07-26T15:00_103",
        "2017-07-26T21:30_104",
        "2017-07-27T09:30_105",
        "2017-07-27T15:00_106",
        "2017-07-27T21:30_111",
        "2017-07-28T09:30_112",
        "2017-07-28T15:15_113",
        "2017-07-28T21:50_114"
      ],
      "nb_amendements": 349,
      "source_url": "http://www.assemblee-nationale.fr/15/ta/ta0009.asp",
      "stage": "1ère lecture",
      "step": "hemicycle"
    },
    {
      "cmp_commission_other_url": "http://www.assemblee-nationale.fr/15/rapports/r0121.asp",
      "date": "2017-08-01",
      "debats_order": 6,
      "directory": "06_cmp_cmp_commission",
      "echec": "échec",
      "enddate": "2017-08-01",
      "institution": "CMP",
      "source_url": "https://www.senat.fr/leg/pjl16-702.html",
      "stage": "CMP",
      "step": "commission"
    },
    {
      "date": "2017-08-01",
      "debats_order": null,
      "directory": "07_nouv.lect._assemblee_depot",
      "enddate": "2017-08-01",
      "institution": "assemblee",
      "source_url": "http://www.assemblee-nationale.fr/15/projets/pl0122.asp",
      "stage": "nouv. lect.",
      "step": "depot"
    },
    {
      "date": "2017-08-02",
      "debats_order": 8,
      "directory": "08_nouv.lect._assemblee_commission",
      "echec": null,
      "enddate": "2017-08-03",
      "has_interventions": true,
      "institution": "assemblee",
      "intervention_files": [
        "2017-08-03T09:30_126",
        "2017-08-03T15:00_127"
      ],
      "nb_amendements": 44,
      "source_url": "http://www.assemblee-nationale.fr/15/ta-commission/r0124-a0.asp",
      "stage": "nouv. lect.",
      "step": "commission"
    },
    {
      "date": "2017-08-03",
      "debats_order": 9,
      "directory": "09_nouv.lect._assemblee_hemicycle",
      "echec": null,
      "enddate": "2017-08-03",
      "has_interventions": true,
      "institution": "assemblee",
      "intervention_files": [
        "2017-07-24T16:00_84",
        "2017-07-24T21:30_85",
        "2017-07-25T15:00_101",
        "2017-07-25T21:30_102",
        "2017-07-26T15:00_103",
        "2017-07-26T21:30_104",
        "2017-07-27T09:30_105",
        "2017-07-27T15:00_106",
        "2017-07-27T21:30_111",
        "2017-07-28T09:30_112",
        "2017-07-28T15:15_113",
        "2017-07-28T21:50_114",
        "2017-08-03T09:30_126",
        "2017-08-03T15:00_127"
      ],
      "nb_amendements": 72,
      "source_url": "http://www.assemblee-nationale.fr/15/ta/ta0017.asp",
      "stage": "nouv. lect.",
      "step": "hemicycle"
    },
    {
      "date": "2017-08-03",
      "debats_order": null,
      "directory": "10_nouv.lect._senat_depot",
      "enddate": "2017-08-03",
      "institution": "senat",
      "source_url": "https://www.senat.fr/leg/pjl16-707.html",
      "stage": "nouv. lect.",
      "step": "depot"
    },
    {
      "date": "2017-08-04",
      "debats_order": 11,
      "directory": "11_nouv.lect._senat_commission",
      "echec": null,
      "enddate": "2017-08-04",
      "institution": "senat",
      "nb_amendements": 33,
      "source_url": "https://www.senat.fr/leg/pjl16-709.html",
      "stage": "nouv. lect.",
      "step": "commission"
    },
    {
      "date": "2017-08-04",
      "debats_order": 12,
      "directory": "12_nouv.lect._senat_hemicycle",
      "echec": null,
      "enddate": "2017-08-04",
      "has_interventions": true,
      "institution": "senat",
      "intervention_files": [
        "2017-08-04T15:00_16548"
      ],
      "nb_amendements": 4,
      "source_url": "https://www.senat.fr/leg/tas16-128.html",
      "stage": "nouv. lect.",
      "step": "hemicycle"
    },
    {
      "date": "2017-08-04",
      "debats_order": null,
      "directory": "13_l.définitive_assemblee_depot",
      "enddate": "2017-08-09",
      "has_interventions": true,
      "institution": "assemblee",
      "intervention_files": [
        "2017-08-09T15:00_131",
        "2017-08-09T15:00_131"
      ],
      "source_url": "http://www.assemblee-nationale.fr/15/ta/ta0017.asp",
      "stage": "l. définitive",
      "step": "depot"
    },
    {
      "date": "2017-08-09",
      "debats_order": 14,
      "directory": "14_l.définitive_assemblee_hemicycle",
      "echec": null,
      "enddate": "2017-08-09",
      "institution": "assemblee",
      "nb_amendements": 24,
      "source_url": "http://www.assemblee-nationale.fr/15/ta/ta0018.asp",
      "stage": "l. définitive",
      "step": "hemicycle"
    },
    {
      "date": "2017-09-08",
      "debats_order": 15,
      "decision": "partiellement conforme",
      "directory": "15_constitutionnalité_conseilconstitutionnel_",
      "echec": null,
      "enddate": "2017-09-08",
      "institution": "conseil constitutionnel",
      "source_url": "https://www.conseil-constitutionnel.fr/decision/2017/2017753DC.htm",
      "stage": "constitutionnalité"
    },
    {
      "date": "2017-09-16",
      "debats_order": null,
      "directory": "16_promulgation_gouvernement_",
      "enddate": "2017-09-16",
      "institution": "gouvernement",
      "source_url": "https://www.legifrance.gouv.fr/affichTexte.do?cidTexte=JORFTEXT000035567936&categorieLien=id",
      "stage": "promulgation"
    }
  ],
  "table_concordance": {
    "10": "18",
    "11": "19",
    "12": "20",
    "13": "21",
    "14": "22",
    "15": "23",
    "16": "24",
    "17": "25",
    "18": "26",
    "19": "27",
    "1er": "1er",
    "1er bis": "2",
    "1er ter": "supprimé",
    "2": "4",
    "2 A": "3",
    "2 B": "supprimé",
    "2 bis": "supprimé",
    "2 bis A": "5",
    "3": "6",
    "4": "7",
    "5": "8",
    "6": "9",
    "6 bis": "10",
    "7": "11",
    "8": "12",
    "8 bis": "supprimé",
    "8 ter": "13",
    "9": "14",
    "9 bis": "15",
    "9 quater": "17",
    "9 quinquies": "supprimé",
    "9 ter": "16"
  },
  "textes_cites": [
    "code électoral",
    "constitution",
    "code pénal"
  ],
  "themes": [
    "Société",
    "Pouvoirs publics et Constitution",
    "Justice"
  ],
  "urgence": true,
  "url_dossier_assemblee": "http://www.assemblee-nationale.fr/dyn/15/dossiers/retablissement_confiance_action_publique",
  "url_dossier_senat": "https://www.senat.fr/dossier-legislatif/pjl16-580.html",
  "url_jo": "https://www.legifrance.gouv.fr/affichTexte.do?cidTexte=JORFTEXT000035567936&categorieLien=id"
}